openmander-0.1.3.dist-info/METADATA
openmander-0.1.3.dist-info/WHEEL
openmander/__init__.py
openmander/openmander.abi3.so
openmander-0.1.3.dist-info/RECORD
