Metadata-Version: 2.4
Name: openmander
Version: 0.1.3
Classifier: Programming Language :: Python :: 3
Classifier: Programming Language :: Rust
Classifier: Operating System :: OS Independent
Summary: OpenMander: a redistricting toolkit in Rust with Python bindings
Author: Benjamin Darnell
Requires-Python: >=3.8
